pogeo.cpython-33m.so
pogeo-0.3.0.dist-info/WHEEL
pogeo-0.3.0.dist-info/DESCRIPTION.rst
pogeo-0.3.0.dist-info/METADATA
pogeo-0.3.0.dist-info/RECORD
pogeo-0.3.0.dist-info/top_level.txt
pogeo-0.3.0.dist-info/metadata.json
