Metadata-Version: 2.0
Name: pogeo
Version: 0.3.0
Summary: Fast geography package.
Home-page: https://github.com/Noctem/pogeo
Author: David Christenson
Author-email: mail@noctem.xyz
License: UNKNOWN
Keywords: pogeo geography S2 distance geo
Platform: UNKNOWN
Classifier: Development Status :: 4 - Beta
Classifier: Intended Audience :: Developers
Classifier: Operating System :: OS Independent
Classifier: Programming Language :: C++
Classifier: Programming Language :: Cython
Classifier: Programming Language :: Python :: 3
Classifier: Programming Language :: Python :: 3.3
Classifier: Programming Language :: Python :: 3.4
Classifier: Programming Language :: Python :: 3.5
Classifier: Programming Language :: Python :: 3.6
Classifier: Topic :: Scientific/Engineering :: GIS
